nads/__init__.py
nads/nads.py
nads/utils.py
nads/visualization.py
nads/compute/__init__.py
nads/compute/gradient_covariance.py
nads/compute/jacobian.py
nads/data/__init__.py
nads/data/dataset.py
nads/data/direction.py
nads-0.0.4.dist-info/LICENSE
nads-0.0.4.dist-info/METADATA
nads-0.0.4.dist-info/WHEEL
nads-0.0.4.dist-info/top_level.txt
nads-0.0.4.dist-info/RECORD
